o1_vector_search/__init__.py
o1_vector_search/core.py
o1_vector_search-1.1.0.dist-info/METADATA
o1_vector_search-1.1.0.dist-info/WHEEL
o1_vector_search-1.1.0.dist-info/top_level.txt
o1_vector_search-1.1.0.dist-info/RECORD
