Metadata-Version: 2.4
Name: o1-vector-search
Version: 1.1.0
Summary: O(1) Vector Search - Instant similarity search with LSH
Home-page: https://github.com/champi-dev/o1-vector-search
Author: Think AI Lab
Author-email: hello@thinkai.dev
Project-URL: Bug Reports, https://github.com/champi-dev/o1-vector-search/issues
Project-URL: Source, https://github.com/champi-dev/o1-vector-search
Keywords: vector-search o1 lsh similarity-search machine-learning ai
Classifier: Development Status :: 5 - Production/Stable
Classifier: Intended Audience :: Developers
Classifier: Topic :: Scientific/Engineering :: Artificial Intelligence
Classifier: License :: OSI Approved :: MIT License
Classifier: Programming Language :: Python :: 3
Classifier: Programming Language :: Python :: 3.8
Classifier: Programming Language :: Python :: 3.9
Classifier: Programming Language :: Python :: 3.10
Classifier: Programming Language :: Python :: 3.11
Classifier: Programming Language :: Python :: 3.12
Requires-Python: >=3.8
Requires-Dist: numpy>=1.19.0
Provides-Extra: dev
Requires-Dist: pytest>=6.0; extra == "dev"
Dynamic: author
Dynamic: author-email
Dynamic: classifier
Dynamic: description
Dynamic: description-content-type
Dynamic: home-page
Dynamic: keywords
Dynamic: project-url
Dynamic: provides-extra
Dynamic: requires-dist
Dynamic: requires-python
Dynamic: summary
